{
  "$schema": "https://raw.githubusercontent.com/spdx/spdx-spec/v2.2.1/schemas/spdx-schema.json",
  "spdxVersion": "SPDX-2.2",
  "dataLicense": "CC0-1.0",
  "SPDXID": "SPDXRef-DOCUMENT",
  "documentNamespace": "https://spdx.org/spdxdocs/tiff-x86-windows-4.5.0#2-8bcd76aa-2be0-4745-b111-168f3b00a3a5",
  "name": "tiff:x86-windows@4.5.0#2 1de70fd8b2dfb225b4e5d92b71f6a986492068c64b73810501d732e2694bd934",
  "creationInfo": {
    "creators": [
      "Tool: vcpkg-8a88d63f241d391772fbde69af9cab96c3c64c75"
    ],
    "created": "2023-02-07T16:34:51Z"
  },
  "relationships": [
    {
      "spdxElementId": "SPDXRef-port",
      "relationshipType": "GENERATES",
      "relatedSpdxElement": "SPDXRef-binary"
    },
    {
      "spdxElementId": "SPDXRef-port",
      "relationshipType": "CONTAINS",
      "relatedSpdxElement": "SPDXRef-file-0"
    },
    {
      "spdxElementId": "SPDXRef-port",
      "relationshipType": "CONTAINS",
      "relatedSpdxElement": "SPDXRef-file-1"
    },
    {
      "spdxElementId": "SPDXRef-port",
      "relationshipType": "CONTAINS",
      "relatedSpdxElement": "SPDXRef-file-2"
    },
    {
      "spdxElementId": "SPDXRef-port",
      "relationshipType": "CONTAINS",
      "relatedSpdxElement": "SPDXRef-file-3"
    },
    {
      "spdxElementId": "SPDXRef-binary",
      "relationshipType": "GENERATED_FROM",
      "relatedSpdxElement": "SPDXRef-port"
    },
    {
      "spdxElementId": "SPDXRef-file-0",
      "relationshipType": "CONTAINED_BY",
      "relatedSpdxElement": "SPDXRef-port"
    },
    {
      "spdxElementId": "SPDXRef-file-1",
      "relationshipType": "CONTAINED_BY",
      "relatedSpdxElement": "SPDXRef-port"
    },
    {
      "spdxElementId": "SPDXRef-file-2",
      "relationshipType": "CONTAINED_BY",
      "relatedSpdxElement": "SPDXRef-port"
    },
    {
      "spdxElementId": "SPDXRef-file-3",
      "relationshipType": "CONTAINED_BY",
      "relatedSpdxElement": "SPDXRef-port"
    },
    {
      "spdxElementId": "SPDXRef-file-3",
      "relationshipType": "DEPENDENCY_MANIFEST_OF",
      "relatedSpdxElement": "SPDXRef-port"
    }
  ],
  "packages": [
    {
      "name": "tiff",
      "SPDXID": "SPDXRef-port",
      "versionInfo": "4.5.0#2",
      "downloadLocation": "git+https://github.com/Microsoft/vcpkg#ports/tiff",
      "homepage": "https://libtiff.gitlab.io/libtiff/",
      "licenseConcluded": "NOASSERTION",
      "licenseDeclared": "NOASSERTION",
      "copyrightText": "NOASSERTION",
      "description": "A library that supports the manipulation of TIFF image files",
      "comment": "This is the port (recipe) consumed by vcpkg."
    },
    {
      "name": "tiff:x86-windows",
      "SPDXID": "SPDXRef-binary",
      "versionInfo": "1de70fd8b2dfb225b4e5d92b71f6a986492068c64b73810501d732e2694bd934",
      "downloadLocation": "NONE",
      "licenseConcluded": "NOASSERTION",
      "licenseDeclared": "NOASSERTION",
      "copyrightText": "NOASSERTION",
      "comment": "This is a binary package built by vcpkg."
    }
  ],
  "files": [
    {
      "fileName": "./FindCMath.patch",
      "SPDXID": "SPDXRef-file-0",
      "checksums": [
        {
          "algorithm": "SHA256",
          "checksumValue": "c7271917f2b3165398ed579ac451c9fc05ddbd4f7854ea3997f731d61aa512c4"
        }
      ],
      "licenseConcluded": "NOASSERTION",
      "copyrightText": "NOASSERTION"
    },
    {
      "fileName": "./portfile.cmake",
      "SPDXID": "SPDXRef-file-1",
      "checksums": [
        {
          "algorithm": "SHA256",
          "checksumValue": "ad5f653b792fb9649300d3c7ff55dda7a301a3dc0761a71f77413de85633726c"
        }
      ],
      "licenseConcluded": "NOASSERTION",
      "copyrightText": "NOASSERTION"
    },
    {
      "fileName": "./vcpkg-cmake-wrapper.cmake.in",
      "SPDXID": "SPDXRef-file-2",
      "checksums": [
        {
          "algorithm": "SHA256",
          "checksumValue": "4affcf46005c51aba5d63882b05e86a91344595e5b870a65a0579a72d8e27bb8"
        }
      ],
      "licenseConcluded": "NOASSERTION",
      "copyrightText": "NOASSERTION"
    },
    {
      "fileName": "./vcpkg.json",
      "SPDXID": "SPDXRef-file-3",
      "checksums": [
        {
          "algorithm": "SHA256",
          "checksumValue": "2cff52cfa4144c3b2bc585aef8b9239639a538751958a522fe4f7dc8d34d98ad"
        }
      ],
      "licenseConcluded": "NOASSERTION",
      "copyrightText": "NOASSERTION"
    }
  ]
}
